easyautomation/__init__.py
easyautomation/keyboard.py
easyautomation/mouse.py
easyautomation-0.1.0.dist-info/LICENSE
easyautomation-0.1.0.dist-info/METADATA
easyautomation-0.1.0.dist-info/WHEEL
easyautomation-0.1.0.dist-info/top_level.txt
easyautomation-0.1.0.dist-info/RECORD
