Metadata-Version: 2.1
Name: easyautomation
Version: 0.1.0
Summary: A keyboard and mouse automation functions package for my own convenience.
Author-email: David Pareja <david@parejarodriguez.com>
License: GNU GENERAL PUBLIC LICENSE
Project-URL: Homepage, https://github.com/Daviid-P/easyautomation
Project-URL: Bug Tracker, https://github.com/Daviid-P/easyautomation/issues
Classifier: Programming Language :: Python :: 3
Classifier: License :: OSI Approved :: GNU General Public License v3 (GPLv3)
Classifier: Operating System :: OS Independent
Requires-Python: >=3.10
License-File: LICENSE
Requires-Dist: opencv-python
Requires-Dist: pyautogui
